click_supercharged/SuperchargedClickGroup.py
click_supercharged/__init__.py
click_supercharged-1.0.0.dist-info/LICENSE
click_supercharged-1.0.0.dist-info/METADATA
click_supercharged-1.0.0.dist-info/WHEEL
click_supercharged-1.0.0.dist-info/top_level.txt
click_supercharged-1.0.0.dist-info/RECORD
