Metadata-Version: 2.2
Name: click-supercharged
Version: 1.0.0
Summary: Click Supercharged is a Python package that enhances the Click command-line framework by adding support for default commands, command aliases, and abbreviations. Simplify command management with features like ambiguity resolution and improved command organization.
Author-email: zirition <zirition@zirition.com>
License: MIT
Project-URL: Homepage, https://github.com/zirition/click-supercharged
Project-URL: Issues, https://github.com/zirition/click-supercharged/issues
Keywords: click,enhacer,default,aliases,abbreviations
Classifier: Programming Language :: Python :: 3
Classifier: Operating System :: OS Independent
Classifier: Topic :: Utilities
Classifier: Environment :: Console
Classifier: Intended Audience :: Developers
Requires-Python: >=3.8
License-File: LICENSE
Requires-Dist: click>=8.1.8
